README.md
setup.py
snapchat/__init__.py
snapchat/snapchat.py
snapchat.egg-info/PKG-INFO
snapchat.egg-info/SOURCES.txt
snapchat.egg-info/dependency_links.txt
snapchat.egg-info/requires.txt
snapchat.egg-info/top_level.txt