Metadata-Version: 2.1
Name: snapchat
Version: 0.1
Summary: Unofficial SnapChat API
Home-page: https://github.com/sdushantha/snapchat
Author: Siddharth Dushantha
Author-email: siddharth.dushantha@gmail.com
License: UNKNOWN
Platform: UNKNOWN
